standardfiles/__init__.py
standardfiles/__main__.py
standardfiles/clear.py
standardfiles/image.py
standardfiles/message.py
standardfiles/name.py
standardfiles/utils.py
standardfiles/file/__init__.py
standardfiles/file/audio.py
standardfiles/file/image.py
standardfiles/file/pdf.py
standardfiles/file/utils.py
standardfiles/file/video.py
standardfiles/options/__init__.py
standardfiles/options/args.py
standardfiles/options/config.py
standardfiles/options/options.py
standardfiles/standard/__init__.py
standardfiles/standard/audio.py
standardfiles/standard/image.py
standardfiles/standard/pdf.py
standardfiles/standard/standard.py
standardfiles/standard/video.py
standardfiles-6.0.dist-info/licenses/LICENSE
standardfiles-6.0.dist-info/METADATA
standardfiles-6.0.dist-info/WHEEL
standardfiles-6.0.dist-info/entry_points.txt
standardfiles-6.0.dist-info/top_level.txt
standardfiles-6.0.dist-info/RECORD
