Metadata-Version: 2.4
Name: standardfiles
Version: 6.0
Summary: Simple python script to convert media to standard format
License-Expression: MIT
Project-URL: Homepage, https://gitlab.com/HansvonHohenstaufen/standardfiles
Project-URL: Repository, https://gitlab.com/HansvonHohenstaufen/standardfiles.git
Project-URL: Issues, https://gitlab.com/HansvonHohenstaufen/standardfiles/-/issues
Classifier: Development Status :: 5 - Production/Stable
Classifier: Intended Audience :: Developers
Classifier: Operating System :: POSIX :: Linux
Classifier: Programming Language :: Python
Classifier: Programming Language :: Python :: 3.13
Requires-Python: >=3.13
License-File: LICENSE
Requires-Dist: setuptools
Requires-Dist: python-magic
Dynamic: license-file
